{"Title": "Counting Bishops", "Category": "Additional Problems", "Time Limit": "1.00 s", "Memory Limit": "512 MB", "Description": "Your task is to count the number of ways k bishops can be placed on an n \\times n chessboard so that no two bishops attack each other. \n Two bishops attack each other if they are on the same diagonal. \n", "Input Specification": "\n The only input line has two integers n and k: the board size and the number of bishops. \n", "Output Specification": "\n Print one integer: the number of ways modulo 10^9+7. \n", "Constraints": "1 \\le n \\le 500\n1 \\le k \\le n^2", "Example Input": "5 4", "Example Output": "2728", "Number": 2176}